{"is_source_file": false, "format": "", "description": "", "external_files": [], "external_methods": [], "published": [], "classes": [], "methods": [], "calls": [], "search-terms": [], "state": 2, "file_id": 13, "knowledge_revision": 44, "git_revision": "88e9836dfe1f541a75b70c95b61e7e8bbfe79bfc", "hash": "7a5cd8320f1acfab397fcf985ac1e0a1", "format-version": 4, "code-base-name": "backend", "filename": "backend/README_FIX_NOTES.md", "revision_history": [{"44": "88e9836dfe1f541a75b70c95b61e7e8bbfe79bfc"}]}